maleo/security/__init__.py
maleo/security/authentication.py
maleo/security/authorization.py
maleo/security/credentials.py
maleo/security/impersonation.py
maleo/security/token.py
maleo_security-0.2.27.dist-info/licenses/LICENSE
maleo_security-0.2.27.dist-info/METADATA
maleo_security-0.2.27.dist-info/WHEEL
maleo_security-0.2.27.dist-info/top_level.txt
maleo_security-0.2.27.dist-info/RECORD
