Metadata-Version: 2.4
Name: maleo-security
Version: 0.2.27
Summary: Security package for MaleoSuite
Author-email: Agra Bima Yuda <agra@nexmedis.com>
License: Proprietary
Requires-Python: >=3.12
License-File: LICENSE
Requires-Dist: annotated-types>=0.7.0
Requires-Dist: anyio>=4.10.0
Requires-Dist: bcrypt>=4.3.0
Requires-Dist: black>=25.1.0
Requires-Dist: cachetools>=5.5.2
Requires-Dist: certifi>=2025.8.3
Requires-Dist: cffi>=2.0.0
Requires-Dist: cfgv>=3.4.0
Requires-Dist: click>=8.2.1
Requires-Dist: colorama>=0.4.6
Requires-Dist: cryptography>=46.0.1
Requires-Dist: distlib>=0.4.0
Requires-Dist: fastapi>=0.116.2
Requires-Dist: filelock>=3.19.1
Requires-Dist: google-auth>=2.40.3
Requires-Dist: h11>=0.16.0
Requires-Dist: httpcore>=1.0.9
Requires-Dist: httpx>=0.28.1
Requires-Dist: identify>=2.6.13
Requires-Dist: idna>=3.10
Requires-Dist: maleo-crypto>=0.0.15
Requires-Dist: maleo-enums>=0.0.25
Requires-Dist: maleo-mixins>=0.0.37
Requires-Dist: maleo-types>=0.0.5
Requires-Dist: mypy_extensions>=1.1.0
Requires-Dist: nodeenv>=1.9.1
Requires-Dist: packaging>=25.0
Requires-Dist: pathspec>=0.12.1
Requires-Dist: platformdirs>=4.4.0
Requires-Dist: pre_commit>=4.3.0
Requires-Dist: pyasn1>=0.6.1
Requires-Dist: pyasn1_modules>=0.4.2
Requires-Dist: pycparser>=2.23
Requires-Dist: pycryptodome>=3.23.0
Requires-Dist: pydantic>=2.11.9
Requires-Dist: pydantic_core>=2.33.2
Requires-Dist: PyJWT>=2.10.1
Requires-Dist: PyYAML>=6.0.2
Requires-Dist: rsa>=4.9.1
Requires-Dist: sniffio>=1.3.1
Requires-Dist: starlette>=0.48.0
Requires-Dist: typing-inspection>=0.4.1
Requires-Dist: typing_extensions>=4.15.0
Requires-Dist: virtualenv>=20.34.0
Dynamic: license-file
